.gitignore
.travis.yml
LICENSE-2.0.txt
README.md
pyproject.toml
setup.cfg
setup.py
tox.ini
example/example.ipynb
faculty_distributed/__init__.py
faculty_distributed/manager.py
faculty_distributed/utils.py
faculty_distributed.egg-info/PKG-INFO
faculty_distributed.egg-info/SOURCES.txt
faculty_distributed.egg-info/dependency_links.txt
faculty_distributed.egg-info/entry_points.txt
faculty_distributed.egg-info/requires.txt
faculty_distributed.egg-info/top_level.txt
faculty_distributed/bin/__init__.py
faculty_distributed/bin/executor.py