Metadata-Version: 1.0
Name: faculty-distributed
Version: 0.1.0
Summary: Distributed execution on faculty platform
Home-page: UNKNOWN
Author: Faculty
Author-email: UNKNOWN
License: Apache Software License
Platform: UNKNOWN
